mcp_test/__init__.py
mcp_test/server.py
mcp_test_demo-0.1.0.dist-info/METADATA
mcp_test_demo-0.1.0.dist-info/WHEEL
mcp_test_demo-0.1.0.dist-info/entry_points.txt
mcp_test_demo-0.1.0.dist-info/RECORD
